source_breezometer/__init__.py
source_breezometer/manifest.yaml
source_breezometer/run.py
source_breezometer/schemas/air_quality_current.json
source_breezometer/schemas/air_quality_forecast.json
source_breezometer/schemas/air_quality_historical.json
source_breezometer/schemas/pollen_forecast.json
source_breezometer/schemas/weather_current.json
source_breezometer/schemas/weather_forecast.json
source_breezometer/schemas/wildfire_burnt_area.json
source_breezometer/schemas/wildfire_locate.json
source_breezometer/source.py
source_breezometer/spec.yaml
airbyte_source_breezometer-0.1.1.dist-info/METADATA
airbyte_source_breezometer-0.1.1.dist-info/WHEEL
airbyte_source_breezometer-0.1.1.dist-info/entry_points.txt
airbyte_source_breezometer-0.1.1.dist-info/RECORD
